sudokusensei/Constants.py
sudokusensei/DB.py
sudokusensei/Main.py
sudokusensei/Profiling.py
sudokusensei/StringBuilder.py
sudokusensei/SudokuGame.py
sudokusensei/SudokuGenerator.py
sudokusensei/SudokuLib.py
sudokusensei/SudokuOptions.py
sudokusensei/SudokuSolver.py
sudokusensei/SudokuUI.py
sudokusensei/TestMain.py
sudokusensei/Version.py
sudokusensei/__init__.py
sudokusensei/data/1052_2020_06_11.sudoku
sudokusensei/data/1055_2020_06_11.sudoku
sudokusensei/data/1154_2020_06_11.sudoku
sudokusensei/data/347_2020_06_11.sudoku
sudokusensei/data/349_2020_06_11.sudoku
sudokusensei/data/350_2020_06_11.sudoku
sudokusensei/data/351.sudoku
sudokusensei/data/351_2020_06_11.sudoku
sudokusensei/data/352_2020_06_11.sudoku
sudokusensei/data/444_2020_06_11.sudoku
sudokusensei/data/446_2020_06_11.sudoku
sudokusensei/data/449_2020_06_11.sudoku
sudokusensei/data/451_2020_06_11.sudoku
sudokusensei/data/452_2020_06_11.sudoku
sudokusensei/data/455_2020_06_11.sudoku
sudokusensei/data/546_2020_06_11.sudoku
sudokusensei/data/648.sudoku
sudokusensei/data/648_2020_06_11.sudoku
sudokusensei/data/649_2020_06_11.sudoku
sudokusensei/data/653_2020_06_11.sudoku
sudokusensei/data/748_2020_06_11.sudoku
sudokusensei/data/752_2020_06_11.sudoku
sudokusensei/data/851_2020_06_11.sudoku
sudokusensei/data/852_2020_06_11.sudoku
sudokusensei/data/853_2020_06_11.sudoku
sudokusensei/data/854_2020_06_11.sudoku
sudokusensei/data/855_2020_06_11.sudoku
sudokusensei/data/951_2020_06_11.sudoku
sudokusensei/data/953_2020_06_11.sudoku
sudokusensei/data/ai_broken_brick.sudoku
sudokusensei/data/ai_circles.sudoku
sudokusensei/data/ai_escargot.sudoku
sudokusensei/data/ai_honeypot.sudoku
sudokusensei/data/ai_killer_application.sudoku
sudokusensei/data/ai_labyrinth.sudoku
sudokusensei/data/ai_lucky_diamond.sudoku
sudokusensei/data/ai_squadron.sudoku
sudokusensei/data/ai_tweezers.sudoku
sudokusensei/data/ai_worm_hole.sudoku
sudokusensei/data/crud.sudoku
sudokusensei/data/debug.sudoku
sudokusensei/data/empty.sudoku
sudokusensei-1.0.1.dist-info/LICENSE.txt
sudokusensei-1.0.1.dist-info/METADATA
sudokusensei-1.0.1.dist-info/WHEEL
sudokusensei-1.0.1.dist-info/entry_points.txt
sudokusensei-1.0.1.dist-info/top_level.txt
sudokusensei-1.0.1.dist-info/RECORD
