Metadata-Version: 2.1
Name: sudokusensei
Version: 1.0.1
Summary: The SMT Sudoku Sensei
Home-page: https://github.com/ianamason/SudokuSensei
Author: Ian A. Mason
Author-email: iam@csl.sri.com
License: CC4
Platform: UNKNOWN
Classifier: Development Status :: 3 - Alpha
Classifier: Natural Language :: English
Classifier: Intended Audience :: Developers
Classifier: License :: OSI Approved :: MIT License
Classifier: Operating System :: OS Independent
Classifier: Programming Language :: C
Classifier: Programming Language :: Python
Classifier: Programming Language :: Python :: 3
Classifier: Programming Language :: Python :: 3.6
Classifier: Programming Language :: Python :: 3.7
Classifier: Programming Language :: Python :: 3.8
Requires-Dist: yices (>=1.1.4)
